nonebot_plugin_hentai_downloader/__init__.py
nonebot_plugin_hentai_downloader/config.py
nonebot_plugin_hentai_downloader-0.2.1.dist-info/licenses/LICENSE
nonebot_plugin_hentai_downloader-0.2.1.dist-info/METADATA
nonebot_plugin_hentai_downloader-0.2.1.dist-info/WHEEL
nonebot_plugin_hentai_downloader-0.2.1.dist-info/top_level.txt
nonebot_plugin_hentai_downloader-0.2.1.dist-info/RECORD
