Metadata-Version: 2.4
Name: nonebot-plugin-hentai-downloader
Version: 0.2.1
Summary: Nonebot2 本子下载
Author-email: padoru233 <padoru233@gmail.com>
Project-URL: Repository, https://github.com/padoru233/nonebot-plugin-hentai-downloader
Requires-Python: <3.13,>=3.10
License-File: LICENSE
Requires-Dist: httpx<1.0.0,>=0.27.0
Requires-Dist: pyminizip>=0.2.6
Requires-Dist: nonebot2>=2.2.0
Requires-Dist: nonebot-plugin-localstore<1.0.0,>=0.7.4
Dynamic: license-file
